Metadata-Version: 1.1
Name: redis-py-cloud
Version: 1.3.8
Summary: Cluster library for redis 5.0.0 built on top of redis-py lib
Home-page: https://github.com/ChinaGoldBear/redis-py-cloud
Author: Max Hua
Author-email: zhhua110@163.com
License: MIT
Keywords: redis,redis cluster
Platform: UNKNOWN
Classifier: Development Status :: 5 - Production/Stable
Classifier: Programming Language :: Python
Classifier: Programming Language :: Python :: 2
Classifier: Programming Language :: Python :: 2.7
Classifier: Programming Language :: Python :: 3
Classifier: Programming Language :: Python :: 3.3
Classifier: Programming Language :: Python :: 3.4
Classifier: Programming Language :: Python :: 3.5
Classifier: Programming Language :: Python :: 3.6
Classifier: Environment :: Web Environment
Classifier: Operating System :: POSIX
Classifier: License :: OSI Approved :: MIT License
